sitetree/__init__.py
sitetree/admin.py
sitetree/apps.py
sitetree/compat.py
sitetree/exceptions.py
sitetree/fields.py
sitetree/forms.py
sitetree/models.py
sitetree/settings.py
sitetree/sitetreeapp.py
sitetree/toolbox.py
sitetree/utils.py
sitetree/locale/de/LC_MESSAGES/django.mo
sitetree/locale/de/LC_MESSAGES/django.po
sitetree/locale/en/LC_MESSAGES/django.po
sitetree/locale/es/LC_MESSAGES/django.mo
sitetree/locale/es/LC_MESSAGES/django.po
sitetree/locale/fa/LC_MESSAGES/django.mo
sitetree/locale/fa/LC_MESSAGES/django.po
sitetree/locale/fr/LC_MESSAGES/django.mo
sitetree/locale/fr/LC_MESSAGES/django.po
sitetree/locale/ja/LC_MESSAGES/django.mo
sitetree/locale/ja/LC_MESSAGES/django.po
sitetree/locale/nb/LC_MESSAGES/django.mo
sitetree/locale/nb/LC_MESSAGES/django.po
sitetree/locale/ru/LC_MESSAGES/django.mo
sitetree/locale/ru/LC_MESSAGES/django.po
sitetree/locale/uk/LC_MESSAGES/django.mo
sitetree/locale/uk/LC_MESSAGES/django.po
sitetree/management/__init__.py
sitetree/management/commands/__init__.py
sitetree/management/commands/sitetree_resync_apps.py
sitetree/management/commands/sitetreedump.py
sitetree/management/commands/sitetreeload.py
sitetree/migrations/0001_initial.py
sitetree/migrations/__init__.py
sitetree/static/css/sitetree_bootstrap_submenu.css
sitetree/templates/admin/sitetree/tree/change_form.html
sitetree/templates/admin/sitetree/tree/change_list_.html
sitetree/templates/admin/sitetree/tree/tree.html
sitetree/templates/admin/sitetree/tree/tree_combo.html
sitetree/templates/admin/sitetree/treeitem/breadcrumbs.html
sitetree/templates/admin/sitetree/treeitem/change_form.html
sitetree/templates/admin/sitetree/treeitem/delete_confirmation.html
sitetree/templates/admin/sitetree/treeitem/object_history.html
sitetree/templates/sitetree/breadcrumbs-title.html
sitetree/templates/sitetree/breadcrumbs.html
sitetree/templates/sitetree/breadcrumbs_bootstrap.html
sitetree/templates/sitetree/breadcrumbs_bootstrap3.html
sitetree/templates/sitetree/breadcrumbs_bootstrap4.html
django_sitetree-1.17.3.dist-info/AUTHORS
django_sitetree-1.17.3.dist-info/LICENSE
django_sitetree-1.17.3.dist-info/METADATA
django_sitetree-1.17.3.dist-info/WHEEL
django_sitetree-1.17.3.dist-info/top_level.txt
django_sitetree-1.17.3.dist-info/RECORD
